assistant_dialog_skill_analysis/__init__.py
assistant_dialog_skill_analysis/confidence_analysis/__init__.py
assistant_dialog_skill_analysis/confidence_analysis/confidence_analyzer.py
assistant_dialog_skill_analysis/data_analysis/__init__.py
assistant_dialog_skill_analysis/data_analysis/divergence_analyzer.py
assistant_dialog_skill_analysis/data_analysis/similarity_analyzer.py
assistant_dialog_skill_analysis/data_analysis/summary_generator.py
assistant_dialog_skill_analysis/experimentation/__init__.py
assistant_dialog_skill_analysis/experimentation/data_manipulator.py
assistant_dialog_skill_analysis/highlighting/__init__.py
assistant_dialog_skill_analysis/highlighting/highlighter.py
assistant_dialog_skill_analysis/inferencing/__init__.py
assistant_dialog_skill_analysis/inferencing/inferencer.py
assistant_dialog_skill_analysis/inferencing/multi_thread_inference.py
assistant_dialog_skill_analysis/resources/cs/stopwords
assistant_dialog_skill_analysis/resources/de/stopwords
assistant_dialog_skill_analysis/resources/en/stopwords
assistant_dialog_skill_analysis/resources/es/stopwords
assistant_dialog_skill_analysis/resources/fr/stopwords
assistant_dialog_skill_analysis/resources/it/stopwords
assistant_dialog_skill_analysis/resources/pt/stopwords
assistant_dialog_skill_analysis/term_analysis/__init__.py
assistant_dialog_skill_analysis/term_analysis/chi2_analyzer.py
assistant_dialog_skill_analysis/term_analysis/entity_analyzer.py
assistant_dialog_skill_analysis/term_analysis/keyword_analyzer.py
assistant_dialog_skill_analysis/utils/__init__.py
assistant_dialog_skill_analysis/utils/lang_utils.py
assistant_dialog_skill_analysis/utils/skills_util.py
assistant_skill_analysis/__init__.py
assistant_skill_analysis/confidence_analysis/__init__.py
assistant_skill_analysis/confidence_analysis/confidence_analyzer.py
assistant_skill_analysis/data_analysis/__init__.py
assistant_skill_analysis/data_analysis/divergence_analyzer.py
assistant_skill_analysis-2.0.1.dist-info/LICENSE
assistant_skill_analysis-2.0.1.dist-info/METADATA
assistant_skill_analysis-2.0.1.dist-info/WHEEL
assistant_skill_analysis-2.0.1.dist-info/top_level.txt
assistant_skill_analysis-2.0.1.dist-info/RECORD
