Metadata-Version: 2.1
Name: assistant-skill-analysis
Version: 2.0.1
Summary: Dialog/Action Skill Analysis Tool for Watson Assistant
Home-page: https://github.com/watson-developer-cloud/assistant-skill-analysis
Author: Haode Qi, Navneet Rao, Ming Tan, Yang Yu, Panos Karagiannis and Ladislav Kunc
Author-email: Haode.Qi@ibm.com, Cheng.qian@ibm.com, lada@ibm.com
License: Apache License 2.0
License-File: LICENSE
Requires-Dist: scikit-learn (>=0.21)
Requires-Dist: numpy (>=1.15.1)
Requires-Dist: pandas
Requires-Dist: tabulate
Requires-Dist: matplotlib
Requires-Dist: nltk
Requires-Dist: seaborn
Requires-Dist: ibm-watson (>=4.5.0)
Requires-Dist: scipy (>=1.2.0)
Requires-Dist: jupyter
Requires-Dist: spacy (~=2.3.2)
Requires-Dist: ibm-cos-sdk (>=2.11.0)
